odoo9_addon_sale_order_product_recommendation-9.0.1.0.0.99.dev5-py3.6-nspkg.pth
odoo_addons/sale_order_product_recommendation/README.rst
odoo_addons/sale_order_product_recommendation/__init__.py
odoo_addons/sale_order_product_recommendation/__openerp__.py
odoo_addons/sale_order_product_recommendation/i18n/ca.po
odoo_addons/sale_order_product_recommendation/i18n/es.po
odoo_addons/sale_order_product_recommendation/i18n/sale_order_product_recommendation.pot
odoo_addons/sale_order_product_recommendation/static/description/icon.png
odoo_addons/sale_order_product_recommendation/tests/__init__.py
odoo_addons/sale_order_product_recommendation/tests/test_recommendation.py
odoo_addons/sale_order_product_recommendation/views/sale_order_view.xml
odoo_addons/sale_order_product_recommendation/wizards/__init__.py
odoo_addons/sale_order_product_recommendation/wizards/sale_order_recommendation.py
odoo_addons/sale_order_product_recommendation/wizards/sale_order_recommendation_view.xml
odoo9_addon_sale_order_product_recommendation-9.0.1.0.0.99.dev5.dist-info/METADATA
odoo9_addon_sale_order_product_recommendation-9.0.1.0.0.99.dev5.dist-info/WHEEL
odoo9_addon_sale_order_product_recommendation-9.0.1.0.0.99.dev5.dist-info/namespace_packages.txt
odoo9_addon_sale_order_product_recommendation-9.0.1.0.0.99.dev5.dist-info/top_level.txt
odoo9_addon_sale_order_product_recommendation-9.0.1.0.0.99.dev5.dist-info/RECORD
